MANIFEST.in
setup.py
vagrantor/__init__.py
vagrantor/__main__.py
vagrantor/validators.py
vagrantor.egg-info/PKG-INFO
vagrantor.egg-info/SOURCES.txt
vagrantor.egg-info/dependency_links.txt
vagrantor.egg-info/entry_points.txt
vagrantor.egg-info/requires.txt
vagrantor.egg-info/top_level.txt
vagrantor/templates/configuration_template.html