Metadata-Version: 1.0
Name: vagrantor
Version: 0.3
Summary: Vagrant configuration file generator
Home-page: https://github.com/bahattincinic/vagrantor
Author: Bahattin Cinic
Author-email: bahattincinic@gmail.com
License: MIT
Platform: UNKNOWN
